pymui/__base__.py
pymui/__init__.py
pymui/license_reference.txt
Pymui-0.0.1.dist-info/LICENSE
Pymui-0.0.1.dist-info/METADATA
Pymui-0.0.1.dist-info/WHEEL
Pymui-0.0.1.dist-info/top_level.txt
Pymui-0.0.1.dist-info/RECORD
