Metadata-Version: 2.1
Name: Pymui
Version: 0.0.1
Summary: A Material UI library for Transcrypt
Home-page: https://github.com/QQuick/Pymui
Author: Jacques de Hooge
Author-email: jacques.de.hooge@qquick.org
License: Apache 2.0
Keywords: transcrypt,react,material,pyact,python,browser
Platform: UNKNOWN
Classifier: Development Status :: 1 - Planning
Classifier: Intended Audience :: Developers
Classifier: Natural Language :: English
Classifier: License :: OSI Approved :: Apache Software License
Classifier: Topic :: Software Development :: Libraries :: Python Modules
Classifier: Operating System :: OS Independent
Classifier: Programming Language :: Python :: 3.9
Requires-Dist: transcrypt
Requires-Dist: pyact
